{"nodes": [{"id": "e_upyojan_applications_amazon_scrapper_package_json", "label": "package.json", "file_type": "code", "source_file": "E:\\upyojan\\Applications\\Amazon_Scrapper\\package.json", "source_location": "L1"}, {"id": "amazon_scrapper_package_name", "label": "name", "file_type": "code", "source_file": "E:\\upyojan\\Applications\\Amazon_Scrapper\\package.json", "source_location": "L2"}, {"id": "amazon_scrapper_package_version", "label": "version", "file_type": "code", "source_file": "E:\\upyojan\\Applications\\Amazon_Scrapper\\package.json", "source_location": "L3"}, {"id": "amazon_scrapper_package_type", "label": "type", "file_type": "code", "source_file": "E:\\upyojan\\Applications\\Amazon_Scrapper\\package.json", "source_location": "L4"}, {"id": "amazon_scrapper_package_description", "label": "description", "file_type": "code", "source_file": "E:\\upyojan\\Applications\\Amazon_Scrapper\\package.json", "source_location": "L5"}, {"id": "amazon_scrapper_package_main", "label": "main", "file_type": "code", "source_file": "E:\\upyojan\\Applications\\Amazon_Scrapper\\package.json", "source_location": "L6"}, {"id": "amazon_scrapper_package_scripts", "label": "scripts", "file_type": "code", "source_file": "E:\\upyojan\\Applications\\Amazon_Scrapper\\package.json", "source_location": "L7"}, {"id": "amazon_scrapper_package_scripts_start", "label": "start", "file_type": "code", "source_file": "E:\\upyojan\\Applications\\Amazon_Scrapper\\package.json", "source_location": "L8"}, {"id": "amazon_scrapper_package_scripts_start_dev", "label": "start:dev", "file_type": "code", "source_file": "E:\\upyojan\\Applications\\Amazon_Scrapper\\package.json", "source_location": "L9"}, {"id": "amazon_scrapper_package_dependencies", "label": "dependencies", "file_type": "code", "source_file": "E:\\upyojan\\Applications\\Amazon_Scrapper\\package.json", "source_location": "L11"}, {"id": "amazon_scrapper_package_dependencies_apify", "label": "apify", "file_type": "code", "source_file": "E:\\upyojan\\Applications\\Amazon_Scrapper\\package.json", "source_location": "L12"}, {"id": "amazon_scrapper_package_dependencies_crawlee", "label": "crawlee", "file_type": "code", "source_file": "E:\\upyojan\\Applications\\Amazon_Scrapper\\package.json", "source_location": "L13"}, {"id": "amazon_scrapper_package_dependencies_playwright", "label": "playwright", "file_type": "code", "source_file": "E:\\upyojan\\Applications\\Amazon_Scrapper\\package.json", "source_location": "L14"}, {"id": "amazon_scrapper_package_engines", "label": "engines", "file_type": "code", "source_file": "E:\\upyojan\\Applications\\Amazon_Scrapper\\package.json", "source_location": "L16"}, {"id": "amazon_scrapper_package_engines_node", "label": "node", "file_type": "code", "source_file": "E:\\upyojan\\Applications\\Amazon_Scrapper\\package.json", "source_location": "L17"}], "edges": [{"source": "e_upyojan_applications_amazon_scrapper_package_json", "target": "amazon_scrapper_package_name", "relation": "contains", "confidence": "EXTRACTED", "source_file": "E:\\upyojan\\Applications\\Amazon_Scrapper\\package.json", "source_location": "L2", "weight": 1.0}, {"source": "e_upyojan_applications_amazon_scrapper_package_json", "target": "amazon_scrapper_package_version", "relation": "contains", "confidence": "EXTRACTED", "source_file": "E:\\upyojan\\Applications\\Amazon_Scrapper\\package.json", "source_location": "L3", "weight": 1.0}, {"source": "e_upyojan_applications_amazon_scrapper_package_json", "target": "amazon_scrapper_package_type", "relation": "contains", "confidence": "EXTRACTED", "source_file": "E:\\upyojan\\Applications\\Amazon_Scrapper\\package.json", "source_location": "L4", "weight": 1.0}, {"source": "e_upyojan_applications_amazon_scrapper_package_json", "target": "amazon_scrapper_package_description", "relation": "contains", "confidence": "EXTRACTED", "source_file": "E:\\upyojan\\Applications\\Amazon_Scrapper\\package.json", "source_location": "L5", "weight": 1.0}, {"source": "e_upyojan_applications_amazon_scrapper_package_json", "target": "amazon_scrapper_package_main", "relation": "contains", "confidence": "EXTRACTED", "source_file": "E:\\upyojan\\Applications\\Amazon_Scrapper\\package.json", "source_location": "L6", "weight": 1.0}, {"source": "e_upyojan_applications_amazon_scrapper_package_json", "target": "amazon_scrapper_package_scripts", "relation": "contains", "confidence": "EXTRACTED", "source_file": "E:\\upyojan\\Applications\\Amazon_Scrapper\\package.json", "source_location": "L7", "weight": 1.0}, {"source": "amazon_scrapper_package_scripts", "target": "amazon_scrapper_package_scripts_start", "relation": "contains", "confidence": "EXTRACTED", "source_file": "E:\\upyojan\\Applications\\Amazon_Scrapper\\package.json", "source_location": "L8", "weight": 1.0}, {"source": "amazon_scrapper_package_scripts", "target": "amazon_scrapper_package_scripts_start_dev", "relation": "contains", "confidence": "EXTRACTED", "source_file": "E:\\upyojan\\Applications\\Amazon_Scrapper\\package.json", "source_location": "L9", "weight": 1.0}, {"source": "e_upyojan_applications_amazon_scrapper_package_json", "target": "amazon_scrapper_package_dependencies", "relation": "contains", "confidence": "EXTRACTED", "source_file": "E:\\upyojan\\Applications\\Amazon_Scrapper\\package.json", "source_location": "L11", "weight": 1.0}, {"source": "amazon_scrapper_package_dependencies", "target": "amazon_scrapper_package_dependencies_apify", "relation": "contains", "confidence": "EXTRACTED", "source_file": "E:\\upyojan\\Applications\\Amazon_Scrapper\\package.json", "source_location": "L12", "weight": 1.0}, {"source": "amazon_scrapper_package_dependencies_apify", "target": "apify", "relation": "imports", "confidence": "EXTRACTED", "source_file": "E:\\upyojan\\Applications\\Amazon_Scrapper\\package.json", "source_location": "L12", "weight": 1.0, "context": "import"}, {"source": "amazon_scrapper_package_dependencies", "target": "amazon_scrapper_package_dependencies_crawlee", "relation": "contains", "confidence": "EXTRACTED", "source_file": "E:\\upyojan\\Applications\\Amazon_Scrapper\\package.json", "source_location": "L13", "weight": 1.0}, {"source": "amazon_scrapper_package_dependencies_crawlee", "target": "crawlee", "relation": "imports", "confidence": "EXTRACTED", "source_file": "E:\\upyojan\\Applications\\Amazon_Scrapper\\package.json", "source_location": "L13", "weight": 1.0, "context": "import"}, {"source": "amazon_scrapper_package_dependencies", "target": "amazon_scrapper_package_dependencies_playwright", "relation": "contains", "confidence": "EXTRACTED", "source_file": "E:\\upyojan\\Applications\\Amazon_Scrapper\\package.json", "source_location": "L14", "weight": 1.0}, {"source": "amazon_scrapper_package_dependencies_playwright", "target": "playwright", "relation": "imports", "confidence": "EXTRACTED", "source_file": "E:\\upyojan\\Applications\\Amazon_Scrapper\\package.json", "source_location": "L14", "weight": 1.0, "context": "import"}, {"source": "e_upyojan_applications_amazon_scrapper_package_json", "target": "amazon_scrapper_package_engines", "relation": "contains", "confidence": "EXTRACTED", "source_file": "E:\\upyojan\\Applications\\Amazon_Scrapper\\package.json", "source_location": "L16", "weight": 1.0}, {"source": "amazon_scrapper_package_engines", "target": "amazon_scrapper_package_engines_node", "relation": "contains", "confidence": "EXTRACTED", "source_file": "E:\\upyojan\\Applications\\Amazon_Scrapper\\package.json", "source_location": "L17", "weight": 1.0}]}